README.md
setup.py
cli/__init__.py
cli/cli.py
src/__init__.py
src/config/__init__.py
src/config/env.py
src/dataclasses/__init__.py
src/dataclasses/model.py
src/dataset/__init__.py
src/dataset/database.py
src/service/__init__.py
src/service/crawler.py
src/service/server.py
src/service/text_similarity.py
src/view/__init__.py
src/view/telegram_bot.py
src/view/telegram_webhook.py
src/view/whatsapp_bot.py
tabayyun_bot.egg-info/PKG-INFO
tabayyun_bot.egg-info/SOURCES.txt
tabayyun_bot.egg-info/dependency_links.txt
tabayyun_bot.egg-info/entry_points.txt
tabayyun_bot.egg-info/not-zip-safe
tabayyun_bot.egg-info/requires.txt
tabayyun_bot.egg-info/top_level.txt