Metadata-Version: 1.2
Name: tabayyun-bot
Version: 1.2.5
Summary: A bot for checking indonesia news and hoaxes
Home-page: UNKNOWN
Author: azzambz
Author-email: zam.badruzaman@gmail.com
License: MIT
Platform: UNKNOWN
Requires-Python: >=3.6
